[
  {
    "competitionId": "test-id",
    "finalJudgeX": 0.623,
    "finalJudgeY": 0.423,
    "winners": [
      {
        "ticketId": "user-1761807965221-6v1cc7gd8:1064",
        "ticketNumber": 1064,
        "participantId": "user-1761807965221-6v1cc7gd8",
        "userId": "user-1761807965221-6v1cc7gd8",
        "participantName": "greeg",
        "participantPhone": "+916565656565",
        "distance": 0.0005099019513592767,
        "marker": {
          "id": "ticket-user-1761807965221-6v1cc7gd8-0-marker-1",
          "x": 0.6229,
          "y": 0.4235
        }
      },
      {
        "ticketId": "user-1761743552569-bf5xta48j:1053",
        "ticketNumber": 1053,
        "participantId": "user-1761743552569-bf5xta48j",
        "userId": "user-1761743552569-bf5xta48j",
        "participantName": "onethree",
        "participantPhone": "+911313131313",
        "distance": 0.012059850745345076,
        "marker": {
          "id": "ticket-user-1761743552569-bf5xta48j-0-marker-1",
          "x": 0.6218,
          "y": 0.435
        }
      },
      {
        "ticketId": "user-1761645213358-25i4wwyev:1040",
        "ticketNumber": 1040,
        "participantId": "user-1761645213358-25i4wwyev",
        "userId": "user-1761645213358-25i4wwyev",
        "participantName": "grt",
        "participantPhone": "+913434343434",
        "distance": 0.04307806866608574,
        "marker": {
          "id": "ticket-user-1761645213358-25i4wwyev-0-marker-1",
          "x": 0.5824,
          "y": 0.4374
        }
      }
    ],
    "computedAt": "2025-10-30T08:38:31.941Z"
  }
]